doif/__init__.py
doif/main.py
doif-0.6.0.dist-info/entry_points.txt
doif-0.6.0.dist-info/WHEEL
doif-0.6.0.dist-info/METADATA
doif-0.6.0.dist-info/RECORD
