Metadata-Version: 2.1
Name: doif
Version: 0.6.0
Summary: TryHackMe
License: MIT
Author: Your Name
Author-email: you@example.com
Requires-Python: >=3.8,<4.0
Classifier: License :: OSI Approved :: MIT License
Classifier: Programming Language :: Python :: 3
Classifier: Programming Language :: Python :: 3.8
Requires-Dist: rich (>=5.2.0,<6.0.0)
